eddy_footprint/__init__.py
eddy_footprint/core.py
eddy_footprint/models.py
eddy_footprint/spatial.py
eddy_footprint-0.2.3.dist-info/LICENSE
eddy_footprint-0.2.3.dist-info/METADATA
eddy_footprint-0.2.3.dist-info/WHEEL
eddy_footprint-0.2.3.dist-info/top_level.txt
eddy_footprint-0.2.3.dist-info/RECORD
